README
blobberc.py
setup.py
blobuploader/__init__.py
blobuploader/cert.py
blobuploader.egg-info/PKG-INFO
blobuploader.egg-info/SOURCES.txt
blobuploader.egg-info/dependency_links.txt
blobuploader.egg-info/requires.txt
blobuploader.egg-info/top_level.txt