Metadata-Version: 1.0
Name: blobuploader
Version: 0.99
Summary: Specific client for uploading blob files on Mozilla server
Home-page: https://github.com/catlee/blobber
Author: Mihai Tabara
Author-email: mtabara@mozilla.com
License: UNKNOWN
Platform: UNKNOWN
